[
    {
        "job_title_name": "Investment Analyst",
        "job_title": "Investment Banking Analyst",
        "company_name": "bangalore strategic solutions",
        "job_description": [
            "Prior internship or work experience in investment banking, corporate finance, or related fields is preferred.",
            "You will assist senior bankers in executing deals,\u2026"
        ],
        "location": "bengaluru"
    },
    {
        "job_title_name": "Investment Analyst",
        "job_title": "Capital Projects Analyst",
        "company_name": "Accenture",
        "job_description": [
            "Years of Experience:3 to 5 years.",
            "Industry X operations enables end-to-end operations integration through data & digital twin to operate client core processes\u2026"
        ],
        "location": "bengaluru"
    },
    {
        "job_title_name": "Investment Analyst",
        "job_title": "Analyst I",
        "company_name": "Northern Trust",
        "job_description": [
            "Major Duties :\u2022 Responsible for ensuring timely and accurate processing of transactions within established guidelines.",
            "Ensures day to day deliverables are met."
        ],
        "location": "bengaluru"
    },
    {
        "job_title_name": "Investment Analyst",
        "job_title": "Business Finance Analyst",
        "company_name": "Flipkart",
        "job_description": [
            "The team drives efficiency in the investment being made to drive topline and customer metrics.",
            "Focus remains on improving category margins and minimizing\u2026"
        ],
        "location": "bengaluru"
    },
    {
        "job_title_name": "Investment Analyst",
        "job_title": "Business Analyst",
        "company_name": "Ethan-Ai India Private Limited",
        "job_description": [
            "Industry Experience: Strong experience in the Wealth Management industry, preferably with wealth management companies, investment firms, or fintech wealth\u2026"
        ],
        "location": "bengaluru"
    },
    {
        "job_title_name": "Investment Analyst",
        "job_title": "Corporate Action and Income Analyst",
        "company_name": "Deutsche Bank",
        "job_description": [
            "2-3 years experience in investment banking operations/ Custody Operations/ Securities Operations with at least 1-2 years of experience in Corporate Actions\u2026"
        ],
        "location": "bengaluru"
    },
    {
        "job_title_name": "Investment Analyst",
        "job_title": "Associate Analyst",
        "company_name": "Wipro Limited",
        "job_description": [
            "Strong interpersonal, Good written and spoken communication skills.",
            "Preferable knowledge on Trade life cycle and capital markets along with various financials\u2026"
        ],
        "location": "bengaluru"
    },
    {
        "job_title_name": "Investment Analyst",
        "job_title": "Research Analyst",
        "company_name": "Synaptic",
        "job_description": [
            "You are intellectually curious and motivated by innovative ideas in the above-mentioned industry sectors and demonstrate an ability to understand, classify,\u2026"
        ],
        "location": "bengaluru"
    },
    {
        "job_title_name": "Investment Analyst",
        "job_title": "EPM Analyst -Associate",
        "company_name": "PwC",
        "job_description": [
            "Invite and give in the moment feedback in a constructive manner.",
            "Share and collaborate effectively with others.",
            "Knowledge on Oracle Cloud infrastructure."
        ],
        "location": "bengaluru"
    },
    {
        "job_title_name": "Investment Analyst",
        "job_title": "Quality Control - Operations Analyst",
        "company_name": "JPMorgan Chase & Co",
        "job_description": [
            "As an Operations analyst you will be accountable to review Quality check on loan documents.",
            "The specialist is accountable to review Quality check on loan\u2026"
        ],
        "location": "bengaluru"
    },
    {
        "job_title_name": "Investment Analyst",
        "job_title": "Business Analyst 2024",
        "company_name": "Ninjacart",
        "job_description": [
            "You will advance Ninjacart\u2019s overall knowledge base by providing analytical rigor and problem solving to our various business investments."
        ],
        "location": "bengaluru"
    }
]