[
    {
        "job_title_name": "Systems Engineer",
        "job_title": "Advisory BMC Engineer (XCC)",
        "company_name": "Lenovo",
        "job_description": [
            "Analyze situations and implement solutions, or develop new system elements, procedures, or processes.",
            "An attractive position is now available for talented\u2026"
        ],
        "location": "bengaluru"
    },
    {
        "job_title_name": "Systems Engineer",
        "job_title": "Senior Software Engineer - Bigdata",
        "company_name": "Clarivate",
        "job_description": [
            "The team consists of 10-12 engineers and is reporting to the Sr Manager.",
            "Our development methodology is Agile , and our system heavily relies on AWS EMR\u2026"
        ],
        "location": "bengaluru"
    },
    {
        "job_title_name": "Systems Engineer",
        "job_title": "Experienced Electronics Systems Design and Analysis Engineer",
        "company_name": "BOEING",
        "job_description": [
            "Tests and validates to ensure system designs meet operational and functional requirements.",
            "Experience in writing Test requirement Documents for various\u2026"
        ],
        "location": "bengaluru"
    },
    {
        "job_title_name": "Systems Engineer",
        "job_title": "Associate Engineer",
        "company_name": "BT",
        "job_description": [
            "Supports the maintenance of systems by monitoring and correcting software defects.",
            "Assists with the implementation of new architectures, standards, and methods\u2026"
        ],
        "location": "bengaluru"
    },
    {
        "job_title_name": "Systems Engineer",
        "job_title": "Senior Systems Engineer - Requirements",
        "company_name": "iCRC",
        "job_description": [
            "Knowledge of railway systems and / or operation within infrastructure projects / technology development and implementation projects."
        ],
        "location": "bengaluru"
    },
    {
        "job_title_name": "Systems Engineer",
        "job_title": "Audio Engineer",
        "company_name": "StratMed",
        "job_description": [
            "Perform audio editing, frame rate conversions and audio conforms on stereo/5.1 audio files for perfect sync.",
            "Individual is responsible for maintaining the audio\u2026"
        ],
        "location": "bengaluru"
    },
    {
        "job_title_name": "Systems Engineer",
        "job_title": "Endpoint Engineer L1",
        "company_name": "Blue Mantis",
        "job_description": [
            "Strong background in MAC OS and Windows Operating systems.",
            "Patching and Endpoint Protection Management: Plan, execute, and manage the patching process for\u2026"
        ],
        "location": "bengaluru"
    },
    {
        "job_title_name": "Systems Engineer",
        "job_title": "Associate Systems Engineer",
        "company_name": "Airbus Group India Private Limited",
        "job_description": [
            "The D&IM Teams based in Bangalore build the Information Management systems and associated competencies that will enable Airbus to \u201cPioneer sustainable aerospace\u2026"
        ],
        "location": "bengaluru"
    },
    {
        "job_title_name": "Systems Engineer",
        "job_title": "Engineer Systems",
        "company_name": "Infineon Technologies",
        "job_description": [
            "Good understanding of RF impairments and system level understanding of RF architectures and their implications on system design.",
            "Knowledge of C++/Tcl/Python/."
        ],
        "location": "bengaluru"
    },
    {
        "job_title_name": "Systems Engineer",
        "job_title": "PMIC Systems & Validation Engineer",
        "company_name": "Qualcomm",
        "job_description": [
            "As a Qualcomm Hardware Engineer, you will plan, design, optimize, verify, and test electronic systems, bring-up yield, circuits, mechanical systems, Digital\u2026"
        ],
        "location": "bengaluru"
    },
    {
        "job_title_name": "Systems Engineer",
        "job_title": "Sr Staff Systems Engineer",
        "company_name": "Wabtec",
        "job_description": [
            "Experience in system level design, including the design of data acquisition systems and the selection and integration of appropriate sensors."
        ],
        "location": "bengaluru"
    }
]