[
    {
        "job_title_name": "Web Developer",
        "job_title": "ReactJS Developer",
        "company_name": "Customer Connect",
        "job_description": [
            "As a developer you are responsible for our current websites.",
            "Importantly, possesses a depth REACT JS knowledge with API Integration."
        ],
        "location": "remote"
    },
    {
        "job_title_name": "Web Developer",
        "job_title": "Frontend Shopify Developer",
        "company_name": "Uplers",
        "job_description": [
            "Producing technical documentation and maintaining code quality through best practices.",
            "Knowledge of SEO principles and their application in ecommerce."
        ],
        "location": "remote"
    },
    {
        "job_title_name": "Web Developer",
        "job_title": "Freelance Web Developer",
        "company_name": "Logical Loopholes",
        "job_description": [
            "CI or Laravel experience as well as expertise with PHP or any other framework.",
            "Excellent working knowledge of Web application development."
        ],
        "location": "remote"
    },
    {
        "job_title_name": "Web Developer",
        "job_title": "Web Developer and Designer",
        "company_name": "Glossaread Technologies Pvt. Ltd",
        "job_description": [
            "Conduct periodic user research (qualitative as well as quantitative methods including in-depth interviews) to understand user needs and to optimize UI/UX design\u2026"
        ],
        "location": "remote"
    },
    {
        "job_title_name": "Web Developer",
        "job_title": "Python Developer",
        "company_name": "edutinker",
        "job_description": [
            "You will also be responsible for integrating the front-end elements built by your co-workers into the application; therefore, a basic understanding of front-end\u2026"
        ],
        "location": "remote"
    },
    {
        "job_title_name": "Web Developer",
        "job_title": "Web Developer",
        "company_name": "Gururo",
        "job_description": [
            "A solid understanding of how web applications work including security, session management, and best development practices.",
            "NET, Javascript or Ruby on Rails."
        ],
        "location": "remote"
    },
    {
        "job_title_name": "Web Developer",
        "job_title": "PHP Web Developer",
        "company_name": "OyeLabs",
        "job_description": [
            "Contribute to design and development of revised application platform on basis of big data technologies that fit current and future data usage scenarios (think\u2026"
        ],
        "location": "remote"
    },
    {
        "job_title_name": "Web Developer",
        "job_title": "Sr. Web Developer",
        "company_name": "BBC Global Services/Snapscale",
        "job_description": [
            "Collaborate with the web development team to fix website issues.",
            "Knowledge of front-end technologies including CSS, HTML.",
            "Graduate in any discipline."
        ],
        "location": "remote"
    },
    {
        "job_title_name": "Web Developer",
        "job_title": "QA Engineer - Frontend (Remote)",
        "company_name": "GreatFrontEnd",
        "job_description": [
            "Can you acknowledge that you are aware that this role will require frontend specific automation testing, as well as regular QA testing, including manual QA?"
        ],
        "location": "remote"
    },
    {
        "job_title_name": "Web Developer",
        "job_title": "Web Designer",
        "company_name": "Probooking.io",
        "job_description": [
            "Collaborate with developers to understand their design requirements and project goals.",
            "Excellent communication skills and the ability to collaborate effectively\u2026"
        ],
        "location": "remote"
    },
    {
        "job_title_name": "Web Developer",
        "job_title": "Wordpress Developer - Website Developer Internship (Remote)",
        "company_name": "NEUONTEK ERA SYSTEMS PRIVATE LIMITED",
        "job_description": [
            "Designing and implementing responsive WordPress websites using best practices.",
            "Knowledge of WordPress security best practices and measures."
        ],
        "location": "remote"
    },
    {
        "job_title_name": "Web Developer",
        "job_title": "Web Developer Intern ( Wordpress)",
        "company_name": "chiramelventures",
        "job_description": [
            "Stay updated with the latest trends and best practices in WordPress development.",
            "Mentorship and guidance from experienced WordPress developers."
        ],
        "location": "remote"
    }
]